loominar/__init__.py
loominar/input_handler.py
loominar/main.py
loominar/api/__init__.py
loominar/api/base_client.py
loominar/api/issues_client.py
loominar/api/metrics_client.py
loominar/api/utils.py
loominar/report/base_report.py
loominar/report/csv_report.py
loominar/report/excel_report.py
loominar/report/report_manager.py
loominar/report/word_report.py
loominar-0.2.0.dist-info/licenses/LICENSE.txt
loominar-0.2.0.dist-info/METADATA
loominar-0.2.0.dist-info/WHEEL
loominar-0.2.0.dist-info/entry_points.txt
loominar-0.2.0.dist-info/top_level.txt
loominar-0.2.0.dist-info/RECORD
